gd_mesh_utils-0.0.2.dist-info/licenses/LICENSE
gdmesh/__init__.py
gdmesh/boundary_edges.py
gdmesh/mesh.py
gdmesh/plotter.py
gdmesh/remesh.py
gdmesh/vtk_ops.py
gd_mesh_utils-0.0.2.dist-info/METADATA
gd_mesh_utils-0.0.2.dist-info/WHEEL
gd_mesh_utils-0.0.2.dist-info/top_level.txt
gd_mesh_utils-0.0.2.dist-info/RECORD
