Metadata-Version: 2.4
Name: gd-mesh-utils
Version: 0.0.2
Requires-Python: <=3.13,>=3.11
License-File: LICENSE
Requires-Dist: gd-py-utils
Requires-Dist: pyvista[all]
Requires-Dist: meshio
Requires-Dist: pymmg[all]
Requires-Dist: ipykernel
Requires-Dist: jupyterlab
Requires-Dist: ipywidgets
Provides-Extra: docs
Requires-Dist: mkdocs; extra == "docs"
Requires-Dist: mkdocs-material; extra == "docs"
Requires-Dist: mkdocs-mermaid2-plugin; extra == "docs"
Requires-Dist: mkdocs-snippets; extra == "docs"
Requires-Dist: mkdocs-exclude; extra == "docs"
Requires-Dist: mkdocstrings-python; extra == "docs"
Dynamic: license-file
